[
    {
        "name": "Azure Functions",
        "yearsExperience": 0.5,
        "description": "Some description",
        "imagePath": "assets/images/programming_languages/vscode.png"
    },
    {
        "name": "Azure API Management",
        "yearsExperience": 0.5,
        "description": "Some description",
        "imagePath": "assets/images/programming_languages/vscode.png"
    },
    {
        "name": "Azure Logic Apps",
        "yearsExperience": 0.5,
        "description": "Some description",
        "imagePath": "assets/images/programming_languages/vscode.png"
    },
    {
        "name": "Azure Servicebus",
        "yearsExperience": 0.5,
        "description": "Some description",
        "imagePath": "assets/images/programming_languages/vscode.png"
    }
]